data_scraper
